evented/__init__.py
evented/base.py
evented/email_watcher.py
evented/event_data.py
evented/event_manager.py
evented/file_watcher.py
evented/helpers.py
evented/log.py
evented/now.py
evented/py.typed
evented/timed_watcher.py
evented/webhook_watcher.py
evented_config/__init__.py
evented_config/configs.py
evented_config/py.typed
evented-1.1.0.dist-info/licenses/LICENSE
evented-1.1.0.dist-info/WHEEL
evented-1.1.0.dist-info/METADATA
evented-1.1.0.dist-info/RECORD
