Metadata-Version: 2.4
Name: evented
Version: 1.1.0
Summary: Event emitters.
Keywords: 
Author: Philipp Temminghoff
Author-email: Philipp Temminghoff <philipptemminghoff@googlemail.com>
License-Expression: MIT
License-File: LICENSE
Classifier: Development Status :: 4 - Beta
Classifier: Framework :: Pydantic
Classifier: Framework :: Pydantic :: 2
Classifier: Intended Audience :: Developers
Classifier: Operating System :: OS Independent
Classifier: Programming Language :: Python :: 3
Classifier: Programming Language :: Python :: 3 :: Only
Classifier: Programming Language :: Python :: 3.12
Classifier: Programming Language :: Python :: 3.13
Classifier: Programming Language :: Python :: 3.14
Classifier: Topic :: Documentation
Classifier: Topic :: Software Development
Classifier: Topic :: Utilities
Classifier: Typing :: Typed
Requires-Dist: anyenv>=1.0.2
Requires-Dist: pydantic
Requires-Dist: schemez
Requires-Dist: watchfiles ; extra == 'all'
Requires-Dist: aioimaplib>=2.0.1 ; extra == 'all'
Requires-Dist: croniter>=6.0.0 ; extra == 'all'
Requires-Dist: fastapi ; extra == 'all'
Requires-Python: >=3.13
Project-URL: Code coverage, https://app.codecov.io/gh/phil65/evented
Project-URL: Discussions, https://github.com/phil65/evented/discussions
Project-URL: Documentation, https://phil65.github.io/evented/
Project-URL: Issues, https://github.com/phil65/evented/issues
Project-URL: Source, https://github.com/phil65/evented
Provides-Extra: all
